{"at":1777664744259,"data":{"asOf":1777664741,"session":"live","horizons":{"daily":{"horizon":"daily","label":"SPX DAILY MODEL","symbol":"^GSPC","displaySymbol":"SPX","spot":7244.33,"spotAnchorDate":"FRI 5/1","targetDate":"FRI 5/1 CLOSE","targetDateLong":"FRI MAY 1, 2026","priceRange":[6763.012483216832,7725.647516783168],"rangeBox":{"low":7219.762751747525,"high":7269.899993079105,"width":50.1372413315803,"widthPct":0.6920894179528031,"breakoutTrigger":7269.899993079105,"breakdownTrigger":7219.762751747525,"status":"contained","anchorHigh":{"name":"CALL WALL","kind":"callWall"},"anchorLow":{"name":"STRONG MAG","kind":"strongMag"}},"levels":[{"label":"T2 UP 7,726","name":"T2 UP","price":7725.647516783168,"kind":"t2Up","distBps":664,"side":"resistance","status":"held"},{"label":"T1 UP 7,485","name":"T1 UP","price":7484.988758391584,"kind":"t1Up","distBps":332,"side":"resistance","status":"held"},{"label":"UPPER VOMMA 7,330","name":"UPPER VOMMA","price":7330.064682677002,"kind":"upperVomma","gex":31244606.58897707,"tag":"TAIL","note":"Upside vomma pocket — IV-churn zone","distBps":118,"side":"resistance","status":"held"},{"label":"UPSIDE PIVOT 7,328","name":"UPSIDE PIVOT","price":7328.059193023738,"kind":"upsidePivot","tag":"VOMMA","distBps":116,"side":"resistance","status":"held"},{"label":"CALL WALL 7,270","name":"CALL WALL","price":7269.899993079105,"kind":"callWall","gex":376919758.845682,"tag":"CEILING","distBps":35,"side":"resistance","status":"held"},{"label":"DOMINANT MAG 7,270","name":"DOMINANT MAG","price":7269.899993079105,"kind":"dominantMag","gex":376919758.845682,"tag":"MAG","distBps":35,"side":"resistance","status":"held"},{"label":"CHARM TGT 7,270","name":"CHARM TARGET","price":7269.899993079105,"kind":"charmTarget","gex":376919758.845682,"tag":"DECAY","note":"Charm-decay magnet — dealers re-hedge toward here into close","distBps":35,"side":"resistance","status":"held"},{"label":"STRONG MAG 7,220","name":"STRONG MAG","price":7219.762751747525,"kind":"strongMag","gex":246560807.96341726,"tag":"MAG","distBps":-34,"side":"support","status":"held"},{"label":"ZOMMA BRIDGE 7,183","name":"ZOMMA BRIDGE","price":7182.937372881356,"kind":"zommaBridge","tag":"SHELF","note":"∂Vega/∂σ shelf — vol-expansion support","distBps":-85,"side":"support","status":"held"},{"label":"EXTREME VAC 7,180","name":"EXTREME VAC","price":7179.652958682261,"kind":"extremeVac","gex":-34108059.45271915,"tag":"VAC","note":"Liquidity vacuum — moves extend here","distBps":-89,"side":"support","status":"held"},{"label":"ZERO-Γ FLIP 7,161","name":"ZERO-Γ FLIP","price":7160.993950389471,"kind":"zeroGamma","tag":"FLIP","distBps":-115,"side":"support","status":"held"},{"label":"MOPEX MAX PAIN 7,099","name":"MOPEX MAX PAIN","price":7099.433372551733,"kind":"mopexMaxPain","tag":"PIN","distBps":-200,"side":"support","status":"held"},{"label":"LOWER VOMMA 7,099","name":"LOWER VOMMA","price":7099.433372551733,"kind":"lowerVomma","gex":70415977.36528814,"tag":"TAIL","note":"Downside vomma pocket — IV-churn zone","distBps":-200,"side":"support","status":"held"},{"label":"DOWNSIDE PIVOT 7,092","name":"DOWNSIDE PIVOT","price":7092.2742149440755,"kind":"downsidePivot","tag":"VOMMA","distBps":-210,"side":"support","status":"held"},{"label":"T1 DOWN 7,004","name":"T1 DOWN","price":7003.671241608416,"kind":"t1Down","distBps":-332,"side":"support","status":"held"},{"label":"PUT WALL 6,969","name":"PUT WALL","price":6969.076545089625,"kind":"putWall","gex":-217463886.60430366,"tag":"FLOOR","distBps":-380,"side":"support","status":"held"},{"label":"T2 DOWN 6,763","name":"T2 DOWN","price":6763.012483216832,"kind":"t2Down","distBps":-664,"side":"support","status":"held"}],"paths":[{"kind":"base","name":"BASE","probability":0.45,"target":7269.899993079105,"waypoints":[{"label":"OPEN","t":0,"price":7244.33},{"label":"10:30","t":0.25,"price":7255.4599859392465},{"label":"12:00","t":0.5,"price":7261.199904073143},{"label":"14:00","t":0.75,"price":7265.846288978094},{"label":"CLOSE 7,270","t":1,"price":7269.899993079105}],"color":"base"},{"kind":"bull","name":"BULL","probability":0.3,"target":7328.059193023738,"waypoints":[{"label":"OPEN","t":0,"price":7244.33},{"label":"10:30","t":0.25,"price":7265.262298255934},{"label":"12:00","t":0.5,"price":7286.194596511868},{"label":"14:00","t":0.75,"price":7307.126894767804},{"label":"CLOSE 7,328","t":1,"price":7328.059193023738}],"color":"bull"},{"kind":"bear","name":"BEAR","probability":0.25,"target":7092.2742149440755,"waypoints":[{"label":"OPEN","t":0,"price":7244.33},{"label":"10:30","t":0.25,"price":7202.6619751947355},{"label":"12:00","t":0.5,"price":7160.993950389471},{"label":"14:00","t":0.75,"price":7126.634082666773},{"label":"CLOSE 7,092","t":1,"price":7092.2742149440755}],"color":"bear"}],"audit":{"asOf":1777664744,"spot":7244.33,"spotChange":"","slope":"DN 1.37° → -2.74","path":"grind down into pin","opexGravity":"200pt below 7,099 ↓ 2.0%","gexTotal":776107126.6445824,"dex":31.876189276896312,"charmPerDay":-2.7382356707088067,"netCTrue":-1383425870.0376701,"vexPerVolPct":0.05769182302635482,"vannaBias":"positive","vannaM":57.7,"gammaZone":"y+","gammaZoneLabel":"DAMPENING","gammaAtSpot":776,"dfi":5,"dfiLabel":"BULLISH","dfiFlipped":false,"contractCount":307,"mainPivot":7160.993950389471,"charmZero":null,"doubleZeroLow":null,"doubleZeroHigh":null,"scenarioProb":{"bull":26,"base":53,"bear":21},"scenarioTargets":{"bull":7286.15,"base":7244.33,"bear":7202.51,"oneDayEM":41.82},"closeTargets":{"bull":{"price":7328.059193023738,"prob":26},"base":{"price":7269.899993079105,"prob":53},"bear":{"price":7092.2742149440755,"prob":21}},"lastRecal":{"at":1777664744,"dfi":5,"dfiDeltaSinceOpen":0},"termStructureDoD":{"iv1d":1.0494813533889542,"iv1dPrev":1.0639699915209746,"iv1dDelta":-0.014488638132020393,"charmNow":-2.74,"charmPrev":-1.1962056523510725,"label":"Charm Pressing"},"charmZeros":[],"charmTightening":{"rate":5.01,"label":"DECEL","chopFlag":true,"note":"DECEL above 3 — charm tightening fast, chop risk into close"},"nearby":[{"price":7330.064682677002,"note":"118bp · UPPER VOMMA","dir":"up"},{"price":7328.059193023738,"note":"116bp · UPSIDE PIVOT","dir":"up"},{"price":7269.899993079105,"note":"35bp · CALL WALL","dir":"up"},{"price":7269.899993079105,"note":"35bp · DOMINANT MAG","dir":"up"},{"price":7269.899993079105,"note":"35bp · CHARM TARGET","dir":"up"},{"price":7219.762751747525,"note":"-34bp · STRONG MAG","dir":"down"}]},"vol":{"vix":16.66,"vixChangePct":-1.3617489518051709,"termRatio":1.2046818727490995,"termLabel":"contango (calm front-end)"},"vomma":"normal","confidence":"LOW","mmMatrix":{"asOf":1777664744,"currentRegime":"CHARM_DRIVEN","currentZone":"CW_TO_0G","regimes":["LONG_GAMMA","NEUTRAL","SHORT_GAMMA","VANNA_DRIVEN","CHARM_DRIVEN"],"zones":["ABOVE_CALL","CW_TO_0G","AT_0G","0G_TO_PW","BELOW_PW"],"cells":[{"regime":"LONG_GAMMA","zone":"ABOVE_CALL","pUp":23,"pDown":46,"pPin":31,"magnitude":50,"action":"fade","bias":-0.23,"intensity":0.75},{"regime":"LONG_GAMMA","zone":"CW_TO_0G","pUp":28,"pDown":16,"pPin":56,"magnitude":33,"action":"pin","bias":0.12,"intensity":0.85},{"regime":"LONG_GAMMA","zone":"AT_0G","pUp":38,"pDown":26,"pPin":36,"magnitude":42,"action":"pin","bias":0.12,"intensity":0.45},{"regime":"LONG_GAMMA","zone":"0G_TO_PW","pUp":38,"pDown":16,"pPin":46,"magnitude":46,"action":"defend","bias":0.22,"intensity":0.6},{"regime":"LONG_GAMMA","zone":"BELOW_PW","pUp":58,"pDown":11,"pPin":31,"magnitude":59,"action":"defend","bias":0.47,"intensity":0.75},{"regime":"NEUTRAL","zone":"ABOVE_CALL","pUp":38,"pDown":36,"pPin":26,"magnitude":78,"action":"fade","bias":0.02,"intensity":0.45},{"regime":"NEUTRAL","zone":"CW_TO_0G","pUp":38,"pDown":26,"pPin":36,"magnitude":52,"action":"pin","bias":0.12,"intensity":0.4},{"regime":"NEUTRAL","zone":"AT_0G","pUp":43,"pDown":31,"pPin":26,"magnitude":65,"action":"fade","bias":0.12,"intensity":0.3},{"regime":"NEUTRAL","zone":"0G_TO_PW","pUp":38,"pDown":31,"pPin":31,"magnitude":71,"action":"accelerate","bias":0.07,"intensity":0.4},{"regime":"NEUTRAL","zone":"BELOW_PW","pUp":43,"pDown":36,"pPin":21,"magnitude":90,"action":"capitulate","bias":0.07,"intensity":0.55},{"regime":"SHORT_GAMMA","zone":"ABOVE_CALL","pUp":63,"pDown":16,"pPin":21,"magnitude":123,"action":"accelerate","bias":0.47,"intensity":0.85},{"regime":"SHORT_GAMMA","zone":"CW_TO_0G","pUp":53,"pDown":21,"pPin":26,"magnitude":82,"action":"accelerate","bias":0.32,"intensity":0.65},{"regime":"SHORT_GAMMA","zone":"AT_0G","pUp":43,"pDown":36,"pPin":21,"magnitude":103,"action":"accelerate","bias":0.07,"intensity":0.7},{"regime":"SHORT_GAMMA","zone":"0G_TO_PW","pUp":28,"pDown":46,"pPin":26,"magnitude":113,"action":"accelerate","bias":-0.18,"intensity":0.8},{"regime":"SHORT_GAMMA","zone":"BELOW_PW","pUp":18,"pDown":61,"pPin":21,"magnitude":144,"action":"capitulate","bias":-0.43,"intensity":0.95},{"regime":"VANNA_DRIVEN","zone":"ABOVE_CALL","pUp":33,"pDown":46,"pPin":21,"magnitude":100,"action":"fade","bias":-0.13,"intensity":0.65},{"regime":"VANNA_DRIVEN","zone":"CW_TO_0G","pUp":38,"pDown":36,"pPin":26,"magnitude":67,"action":"fade","bias":0.02,"intensity":0.55},{"regime":"VANNA_DRIVEN","zone":"AT_0G","pUp":38,"pDown":31,"pPin":31,"magnitude":84,"action":"fade","bias":0.07,"intensity":0.4},{"regime":"VANNA_DRIVEN","zone":"0G_TO_PW","pUp":33,"pDown":41,"pPin":26,"magnitude":92,"action":"accelerate","bias":-0.08,"intensity":0.7},{"regime":"VANNA_DRIVEN","zone":"BELOW_PW","pUp":28,"pDown":51,"pPin":21,"magnitude":117,"action":"capitulate","bias":-0.23,"intensity":0.85},{"regime":"CHARM_DRIVEN","zone":"ABOVE_CALL","pUp":31,"pDown":49,"pPin":20,"magnitude":64,"action":"fade","bias":-0.18,"intensity":0.7},{"regime":"CHARM_DRIVEN","zone":"CW_TO_0G","pUp":24,"pDown":36,"pPin":40,"magnitude":43,"action":"pin","bias":-0.12,"intensity":0.65},{"regime":"CHARM_DRIVEN","zone":"AT_0G","pUp":31,"pDown":19,"pPin":50,"magnitude":53,"action":"pin","bias":0.12,"intensity":0.9},{"regime":"CHARM_DRIVEN","zone":"0G_TO_PW","pUp":46,"pDown":14,"pPin":40,"magnitude":59,"action":"pin","bias":0.32,"intensity":0.65},{"regime":"CHARM_DRIVEN","zone":"BELOW_PW","pUp":61,"pDown":19,"pPin":20,"magnitude":75,"action":"defend","bias":0.42,"intensity":0.7}],"notes":{"regime":"OPEX proximity (0D) + charm tightening — delta rebalance pressure into close","zone":"Between 0-Γ (7161) and Call Wall (7270) — hugging CW positive gamma","summary":"Dealers likely pin spot — 40% pinned, ~43pt move"}}},"weekly":{"horizon":"weekly","label":"SPX WEEKLY MODEL","symbol":"^GSPC","displaySymbol":"SPX","spot":7244.33,"spotAnchorDate":"FRI 5/1","targetDate":"FRI 5/1","targetDateLong":"FRI MAY 1, 2026","priceRange":[6843.23206934736,7645.42793065264],"rangeBox":{"low":7219.762751747525,"high":7269.899993079105,"width":50.1372413315803,"widthPct":0.6920894179528031,"breakoutTrigger":7269.899993079105,"breakdownTrigger":7219.762751747525,"status":"contained","anchorHigh":{"name":"CALL WALL","kind":"callWall"},"anchorLow":{"name":"STRONG MAG","kind":"strongMag"}},"levels":[{"label":"T2 UP 7,645","name":"T2 UP","price":7645.42793065264,"kind":"t2Up","distBps":554,"side":"resistance","status":"held"},{"label":"T1 UP 7,445","name":"T1 UP","price":7444.878965326319,"kind":"t1Up","distBps":277,"side":"resistance","status":"held"},{"label":"UPPER VOMMA 7,420","name":"UPPER VOMMA","price":7420.311717073845,"kind":"upperVomma","gex":41965947.27097724,"tag":"TAIL","note":"Upside vomma pocket — IV-churn zone","distBps":243,"side":"resistance","status":"held"},{"label":"UPSIDE PIVOT 7,328","name":"UPSIDE PIVOT","price":7328.059193023738,"kind":"upsidePivot","tag":"VOMMA","distBps":116,"side":"resistance","status":"held"},{"label":"CALL WALL 7,270","name":"CALL WALL","price":7269.899993079105,"kind":"callWall","gex":872794024.0226133,"tag":"CEILING","distBps":35,"side":"resistance","status":"held"},{"label":"DOMINANT MAG 7,270","name":"DOMINANT MAG","price":7269.899993079105,"kind":"dominantMag","gex":752971321.5631117,"tag":"MAG","distBps":35,"side":"resistance","status":"held"},{"label":"CHARM TGT 7,270","name":"CHARM TARGET","price":7269.899993079105,"kind":"charmTarget","gex":752971321.5631117,"tag":"DECAY","note":"Charm-decay magnet — dealers re-hedge toward here into close","distBps":35,"side":"resistance","status":"held"},{"label":"STRONG MAG 7,220","name":"STRONG MAG","price":7219.762751747525,"kind":"strongMag","gex":434321055.055832,"tag":"MAG","distBps":-34,"side":"support","status":"held"},{"label":"ZOMMA BRIDGE 7,207","name":"ZOMMA BRIDGE","price":7207.494423728814,"kind":"zommaBridge","tag":"SHELF","note":"∂Vega/∂σ shelf — vol-expansion support","distBps":-51,"side":"support","status":"held"},{"label":"ZERO-Γ FLIP 7,193","name":"ZERO-Γ FLIP","price":7192.810695903064,"kind":"zeroGamma","tag":"FLIP","distBps":-71,"side":"support","status":"held"},{"label":"MOPEX MAX PAIN 7,119","name":"MOPEX MAX PAIN","price":7119.488269084365,"kind":"mopexMaxPain","tag":"PIN","distBps":-172,"side":"support","status":"held"},{"label":"T1 DOWN 7,044","name":"T1 DOWN","price":7043.781034673681,"kind":"t1Down","distBps":-277,"side":"support","status":"held"},{"label":"PUT WALL 7,019","name":"PUT WALL","price":7019.213786421205,"kind":"putWall","gex":-549267053.8198621,"tag":"FLOOR","distBps":-311,"side":"support","status":"held"},{"label":"EXTREME VAC 7,019","name":"EXTREME VAC","price":7019.213786421205,"kind":"extremeVac","gex":-487773792.6960986,"tag":"VAC","note":"Liquidity vacuum — moves extend here","distBps":-311,"side":"support","status":"held"},{"label":"LOWER VOMMA 7,019","name":"LOWER VOMMA","price":7019.213786421205,"kind":"lowerVomma","gex":-487773792.6960986,"tag":"TAIL","note":"Downside vomma pocket — IV-churn zone","distBps":-311,"side":"support","status":"held"},{"label":"DOWNSIDE PIVOT 6,984","name":"DOWNSIDE PIVOT","price":6984.117717489099,"kind":"downsidePivot","tag":"VOMMA","distBps":-359,"side":"support","status":"held"},{"label":"T2 DOWN 6,843","name":"T2 DOWN","price":6843.23206934736,"kind":"t2Down","distBps":-554,"side":"support","status":"held"}],"paths":[{"kind":"base","name":"BASE","probability":0.45,"target":7269.899993079105,"waypoints":[{"label":"MON 4/27","t":0,"price":7244.33},{"label":"TUE 4/28","t":0.25,"price":7255.4599859392465},{"label":"WED 4/29","t":0.5,"price":7261.199904073143},{"label":"THU 4/30","t":0.75,"price":7265.846288978094},{"label":"FRI 5/1 7,270","t":1,"price":7269.899993079105}],"color":"base"},{"kind":"bull","name":"BULL","probability":0.3,"target":7328.059193023738,"waypoints":[{"label":"MON 4/27","t":0,"price":7244.33},{"label":"TUE 4/28","t":0.25,"price":7265.262298255934},{"label":"WED 4/29","t":0.5,"price":7286.194596511868},{"label":"THU 4/30","t":0.75,"price":7307.126894767804},{"label":"FRI 5/1 7,328","t":1,"price":7328.059193023738}],"color":"bull"},{"kind":"bear","name":"BEAR","probability":0.25,"target":6984.117717489099,"waypoints":[{"label":"MON 4/27","t":0,"price":7244.33},{"label":"TUE 4/28","t":0.25,"price":7218.570347951532},{"label":"WED 4/29","t":0.5,"price":7192.810695903064},{"label":"THU 4/30","t":0.75,"price":7088.464206696081},{"label":"FRI 5/1 6,984","t":1,"price":6984.117717489099}],"color":"bear"}],"audit":{"asOf":1777664743,"spot":7244.33,"spotChange":"","slope":"DN 1.66° → -3.31","path":"grind down into pin","opexGravity":"172pt below 7,119 ↓ 1.7%","gexTotal":2496401379.029398,"dex":51.446881210603486,"charmPerDay":-3.3110726858084067,"netCTrue":-1672837608.5820024,"vexPerVolPct":0.44746236543168777,"vannaBias":"positive","vannaM":447.5,"gammaZone":"y+","gammaZoneLabel":"DAMPENING","gammaAtSpot":2496,"dfi":5,"dfiLabel":"BULLISH","dfiFlipped":false,"contractCount":1293,"mainPivot":7192.810695903064,"charmZero":null,"doubleZeroLow":null,"doubleZeroHigh":null,"scenarioProb":{"bull":26,"base":53,"bear":21},"scenarioTargets":{"bull":7286.15,"base":7244.33,"bear":7202.51,"oneDayEM":41.82},"closeTargets":{"bull":{"price":7328.059193023738,"prob":26},"base":{"price":7269.899993079105,"prob":53},"bear":{"price":6984.117717489099,"prob":21}},"lastRecal":{"at":1777664743,"dfi":5,"dfiDeltaSinceOpen":0},"termStructureDoD":{"iv1d":1.0494813533889542,"iv1dPrev":1.0639699915209746,"iv1dDelta":-0.014488638132020393,"charmNow":-3.31,"charmPrev":-1.704775734154393,"label":"Charm Pressing"},"charmZeros":[],"charmTightening":{"rate":10.78,"label":"DECEL","chopFlag":true,"note":"DECEL above 3 — charm tightening fast, chop risk into close"},"nearby":[{"price":7420.311717073845,"note":"243bp · UPPER VOMMA","dir":"up"},{"price":7328.059193023738,"note":"116bp · UPSIDE PIVOT","dir":"up"},{"price":7269.899993079105,"note":"35bp · CALL WALL","dir":"up"},{"price":7269.899993079105,"note":"35bp · DOMINANT MAG","dir":"up"},{"price":7269.899993079105,"note":"35bp · CHARM TARGET","dir":"up"},{"price":7219.762751747525,"note":"-34bp · STRONG MAG","dir":"down"}]},"vol":{"vix":16.66,"vixChangePct":-1.3617489518051709,"termRatio":1.2046818727490995,"termLabel":"contango (calm front-end)"},"vomma":"normal","confidence":"MODERATE","mmMatrix":{"asOf":1777664743,"currentRegime":"CHARM_DRIVEN","currentZone":"CW_TO_0G","regimes":["LONG_GAMMA","NEUTRAL","SHORT_GAMMA","VANNA_DRIVEN","CHARM_DRIVEN"],"zones":["ABOVE_CALL","CW_TO_0G","AT_0G","0G_TO_PW","BELOW_PW"],"cells":[{"regime":"LONG_GAMMA","zone":"ABOVE_CALL","pUp":23,"pDown":46,"pPin":31,"magnitude":112,"action":"fade","bias":-0.23,"intensity":0.75},{"regime":"LONG_GAMMA","zone":"CW_TO_0G","pUp":28,"pDown":16,"pPin":56,"magnitude":75,"action":"pin","bias":0.12,"intensity":0.85},{"regime":"LONG_GAMMA","zone":"AT_0G","pUp":38,"pDown":26,"pPin":36,"magnitude":94,"action":"pin","bias":0.12,"intensity":0.45},{"regime":"LONG_GAMMA","zone":"0G_TO_PW","pUp":38,"pDown":16,"pPin":46,"magnitude":103,"action":"defend","bias":0.22,"intensity":0.6},{"regime":"LONG_GAMMA","zone":"BELOW_PW","pUp":58,"pDown":11,"pPin":31,"magnitude":131,"action":"defend","bias":0.47,"intensity":0.75},{"regime":"NEUTRAL","zone":"ABOVE_CALL","pUp":38,"pDown":36,"pPin":26,"magnitude":173,"action":"fade","bias":0.02,"intensity":0.45},{"regime":"NEUTRAL","zone":"CW_TO_0G","pUp":38,"pDown":26,"pPin":36,"magnitude":116,"action":"pin","bias":0.12,"intensity":0.4},{"regime":"NEUTRAL","zone":"AT_0G","pUp":43,"pDown":31,"pPin":26,"magnitude":145,"action":"fade","bias":0.12,"intensity":0.3},{"regime":"NEUTRAL","zone":"0G_TO_PW","pUp":38,"pDown":31,"pPin":31,"magnitude":159,"action":"accelerate","bias":0.07,"intensity":0.4},{"regime":"NEUTRAL","zone":"BELOW_PW","pUp":43,"pDown":36,"pPin":21,"magnitude":202,"action":"capitulate","bias":0.07,"intensity":0.55},{"regime":"SHORT_GAMMA","zone":"ABOVE_CALL","pUp":63,"pDown":16,"pPin":21,"magnitude":275,"action":"accelerate","bias":0.47,"intensity":0.85},{"regime":"SHORT_GAMMA","zone":"CW_TO_0G","pUp":53,"pDown":21,"pPin":26,"magnitude":184,"action":"accelerate","bias":0.32,"intensity":0.65},{"regime":"SHORT_GAMMA","zone":"AT_0G","pUp":43,"pDown":36,"pPin":21,"magnitude":230,"action":"accelerate","bias":0.07,"intensity":0.7},{"regime":"SHORT_GAMMA","zone":"0G_TO_PW","pUp":28,"pDown":46,"pPin":26,"magnitude":252,"action":"accelerate","bias":-0.18,"intensity":0.8},{"regime":"SHORT_GAMMA","zone":"BELOW_PW","pUp":18,"pDown":61,"pPin":21,"magnitude":321,"action":"capitulate","bias":-0.43,"intensity":0.95},{"regime":"VANNA_DRIVEN","zone":"ABOVE_CALL","pUp":33,"pDown":46,"pPin":21,"magnitude":224,"action":"fade","bias":-0.13,"intensity":0.65},{"regime":"VANNA_DRIVEN","zone":"CW_TO_0G","pUp":38,"pDown":36,"pPin":26,"magnitude":150,"action":"fade","bias":0.02,"intensity":0.55},{"regime":"VANNA_DRIVEN","zone":"AT_0G","pUp":38,"pDown":31,"pPin":31,"magnitude":187,"action":"fade","bias":0.07,"intensity":0.4},{"regime":"VANNA_DRIVEN","zone":"0G_TO_PW","pUp":33,"pDown":41,"pPin":26,"magnitude":206,"action":"accelerate","bias":-0.08,"intensity":0.7},{"regime":"VANNA_DRIVEN","zone":"BELOW_PW","pUp":28,"pDown":51,"pPin":21,"magnitude":262,"action":"capitulate","bias":-0.23,"intensity":0.85},{"regime":"CHARM_DRIVEN","zone":"ABOVE_CALL","pUp":31,"pDown":49,"pPin":20,"magnitude":143,"action":"fade","bias":-0.18,"intensity":0.7},{"regime":"CHARM_DRIVEN","zone":"CW_TO_0G","pUp":25,"pDown":35,"pPin":40,"magnitude":95,"action":"pin","bias":-0.1,"intensity":0.65},{"regime":"CHARM_DRIVEN","zone":"AT_0G","pUp":31,"pDown":19,"pPin":50,"magnitude":119,"action":"pin","bias":0.12,"intensity":0.9},{"regime":"CHARM_DRIVEN","zone":"0G_TO_PW","pUp":46,"pDown":14,"pPin":40,"magnitude":131,"action":"pin","bias":0.32,"intensity":0.65},{"regime":"CHARM_DRIVEN","zone":"BELOW_PW","pUp":61,"pDown":19,"pPin":20,"magnitude":167,"action":"defend","bias":0.42,"intensity":0.7}],"notes":{"regime":"OPEX proximity (0D) + charm tightening — delta rebalance pressure into close","zone":"Between 0-Γ (7193) and Call Wall (7270) — mid-range positive gamma","summary":"Dealers likely pin spot — 40% pinned, ~95pt move"}}},"monthly":{"horizon":"monthly","label":"SPX MONTHLY MODEL","symbol":"^GSPC","displaySymbol":"SPX","spot":7244.33,"spotAnchorDate":"FRI 5/1","targetDate":"FRI 5/15","targetDateLong":"FRI MAY 15, 2026","priceRange":[6843.23206934736,7645.42793065264],"rangeBox":{"low":7219.762751747525,"high":7269.899993079105,"width":50.1372413315803,"widthPct":0.6920894179528031,"breakoutTrigger":7269.899993079105,"breakdownTrigger":7219.762751747525,"status":"contained","anchorHigh":{"name":"CALL WALL","kind":"callWall"},"anchorLow":{"name":"STRONG MAG","kind":"strongMag"}},"levels":[{"label":"T2 UP 7,645","name":"T2 UP","price":7645.42793065264,"kind":"t2Up","distBps":554,"side":"resistance","status":"held"},{"label":"UPPER VOMMA 7,621","name":"UPPER VOMMA","price":7620.860682400165,"kind":"upperVomma","gex":47019866.22991816,"tag":"TAIL","note":"Upside vomma pocket — IV-churn zone","distBps":520,"side":"resistance","status":"held"},{"label":"UPSIDE PIVOT 7,549","name":"UPSIDE PIVOT","price":7549.008664256164,"kind":"upsidePivot","tag":"VOMMA","distBps":421,"side":"resistance","status":"held"},{"label":"VANNA FLIP 7,549","name":"VANNA FLIP","price":7549.008664256164,"kind":"vannaFlip","tag":"VANNA","note":"Sign change in ∂Δ/∂σ — hedge direction flips here","distBps":421,"side":"resistance","status":"held"},{"label":"T1 UP 7,445","name":"T1 UP","price":7444.878965326319,"kind":"t1Up","distBps":277,"side":"resistance","status":"held"},{"label":"CALL WALL 7,270","name":"CALL WALL","price":7269.899993079105,"kind":"callWall","gex":1156909563.11833,"tag":"CEILING","distBps":35,"side":"resistance","status":"held"},{"label":"DOMINANT MAG 7,270","name":"DOMINANT MAG","price":7269.899993079105,"kind":"dominantMag","gex":991838096.1627138,"tag":"MAG","distBps":35,"side":"resistance","status":"held"},{"label":"CHARM TGT 7,270","name":"CHARM TARGET","price":7269.899993079105,"kind":"charmTarget","gex":991838096.1627138,"tag":"DECAY","note":"Charm-decay magnet — dealers re-hedge toward here into close","distBps":35,"side":"resistance","status":"held"},{"label":"STRONG MAG 7,220","name":"STRONG MAG","price":7219.762751747525,"kind":"strongMag","gex":757524067.2862246,"tag":"MAG","distBps":-34,"side":"support","status":"held"},{"label":"ZOMMA BRIDGE 7,207","name":"ZOMMA BRIDGE","price":7207.494423728814,"kind":"zommaBridge","tag":"SHELF","note":"∂Vega/∂σ shelf — vol-expansion support","distBps":-51,"side":"support","status":"held"},{"label":"ZERO-Γ FLIP 7,204","name":"ZERO-Γ FLIP","price":7203.522271581031,"kind":"zeroGamma","tag":"FLIP","distBps":-56,"side":"support","status":"held"},{"label":"MOPEX MAX PAIN 7,059","name":"MOPEX MAX PAIN","price":7059.323579486469,"kind":"mopexMaxPain","tag":"PIN","distBps":-255,"side":"support","status":"held"},{"label":"T1 DOWN 7,044","name":"T1 DOWN","price":7043.781034673681,"kind":"t1Down","distBps":-277,"side":"support","status":"held"},{"label":"PUT WALL 7,019","name":"PUT WALL","price":7019.213786421205,"kind":"putWall","gex":-1075529511.2166183,"tag":"FLOOR","distBps":-311,"side":"support","status":"held"},{"label":"EXTREME VAC 7,019","name":"EXTREME VAC","price":7019.213786421205,"kind":"extremeVac","gex":-759438361.0136092,"tag":"VAC","note":"Liquidity vacuum — moves extend here","distBps":-311,"side":"support","status":"held"},{"label":"DOWNSIDE PIVOT 6,984","name":"DOWNSIDE PIVOT","price":6984.117717489099,"kind":"downsidePivot","tag":"VOMMA","distBps":-359,"side":"support","status":"held"},{"label":"T2 DOWN 6,843","name":"T2 DOWN","price":6843.23206934736,"kind":"t2Down","distBps":-554,"side":"support","status":"held"},{"label":"LOWER VOMMA 6,819","name":"LOWER VOMMA","price":6818.664821094885,"kind":"lowerVomma","gex":-327111630.23404956,"tag":"TAIL","note":"Downside vomma pocket — IV-churn zone","distBps":-588,"side":"support","status":"held"}],"paths":[{"kind":"base","name":"BASE","probability":0.45,"target":7269.899993079105,"waypoints":[{"label":"FRI 5/1","t":0,"price":7244.33},{"label":"FRI 5/8 7,270","t":1,"price":7269.899993079105}],"color":"base"},{"kind":"bull","name":"BULL","probability":0.3,"target":7549.008664256164,"waypoints":[{"label":"FRI 5/1","t":0,"price":7244.33},{"label":"FRI 5/8 7,549","t":1,"price":7549.008664256164}],"color":"bull"},{"kind":"bear","name":"BEAR","probability":0.25,"target":6984.117717489099,"waypoints":[{"label":"FRI 5/1","t":0,"price":7244.33},{"label":"FRI 5/8 6,984","t":1,"price":6984.117717489099}],"color":"bear"}],"audit":{"asOf":1777664744,"spot":7244.33,"spotChange":"","slope":"DN 1.97° → -3.94","path":"grind down into pin","opexGravity":"255pt below 7,059 ↓ 2.5%","gexTotal":2666689707.4016848,"dex":107.21164124492853,"charmPerDay":-3.9427162649765473,"netCTrue":-1991959909.6358788,"vexPerVolPct":1.5006057517023426,"vannaBias":"positive","vannaM":1500.6,"gammaZone":"y+","gammaZoneLabel":"DAMPENING","gammaAtSpot":2667,"dfi":5,"dfiLabel":"BULLISH","dfiFlipped":false,"contractCount":3335,"mainPivot":7203.522271581031,"charmZero":null,"doubleZeroLow":null,"doubleZeroHigh":null,"scenarioProb":{"bull":26,"base":53,"bear":21},"scenarioTargets":{"bull":7286.15,"base":7244.33,"bear":7202.51,"oneDayEM":41.82},"closeTargets":{"bull":{"price":7549.008664256164,"prob":26},"base":{"price":7269.899993079105,"prob":53},"bear":{"price":6984.117717489099,"prob":21}},"lastRecal":{"at":1777664744,"dfi":5,"dfiDeltaSinceOpen":0},"termStructureDoD":{"iv1d":1.0494813533889542,"iv1dPrev":1.0639699915209746,"iv1dDelta":-0.014488638132020393,"charmNow":-3.94,"charmPrev":-2.33612815907137,"label":"Charm Pressing"},"charmZeros":[],"charmTightening":{"rate":12.36,"label":"DECEL","chopFlag":true,"note":"DECEL above 3 — charm tightening fast, chop risk into close"},"nearby":[{"price":7620.860682400165,"note":"520bp · UPPER VOMMA","dir":"up"},{"price":7549.008664256164,"note":"421bp · UPSIDE PIVOT","dir":"up"},{"price":7549.008664256164,"note":"421bp · VANNA FLIP","dir":"up"},{"price":7269.899993079105,"note":"35bp · CALL WALL","dir":"up"},{"price":7269.899993079105,"note":"35bp · DOMINANT MAG","dir":"up"},{"price":7269.899993079105,"note":"35bp · CHARM TARGET","dir":"up"}]},"vol":{"vix":16.66,"vixChangePct":-1.3617489518051709,"termRatio":1.2046818727490995,"termLabel":"contango (calm front-end)"},"vomma":"normal","confidence":"MODERATE","mmMatrix":{"asOf":1777664744,"currentRegime":"CHARM_DRIVEN","currentZone":"CW_TO_0G","regimes":["LONG_GAMMA","NEUTRAL","SHORT_GAMMA","VANNA_DRIVEN","CHARM_DRIVEN"],"zones":["ABOVE_CALL","CW_TO_0G","AT_0G","0G_TO_PW","BELOW_PW"],"cells":[{"regime":"LONG_GAMMA","zone":"ABOVE_CALL","pUp":23,"pDown":46,"pPin":31,"magnitude":230,"action":"fade","bias":-0.23,"intensity":0.75},{"regime":"LONG_GAMMA","zone":"CW_TO_0G","pUp":28,"pDown":16,"pPin":56,"magnitude":153,"action":"pin","bias":0.12,"intensity":0.85},{"regime":"LONG_GAMMA","zone":"AT_0G","pUp":38,"pDown":26,"pPin":36,"magnitude":192,"action":"pin","bias":0.12,"intensity":0.45},{"regime":"LONG_GAMMA","zone":"0G_TO_PW","pUp":38,"pDown":16,"pPin":46,"magnitude":211,"action":"defend","bias":0.22,"intensity":0.6},{"regime":"LONG_GAMMA","zone":"BELOW_PW","pUp":58,"pDown":11,"pPin":31,"magnitude":268,"action":"defend","bias":0.47,"intensity":0.75},{"regime":"NEUTRAL","zone":"ABOVE_CALL","pUp":38,"pDown":36,"pPin":26,"magnitude":355,"action":"fade","bias":0.02,"intensity":0.45},{"regime":"NEUTRAL","zone":"CW_TO_0G","pUp":38,"pDown":26,"pPin":36,"magnitude":237,"action":"pin","bias":0.12,"intensity":0.4},{"regime":"NEUTRAL","zone":"AT_0G","pUp":43,"pDown":31,"pPin":26,"magnitude":296,"action":"fade","bias":0.12,"intensity":0.3},{"regime":"NEUTRAL","zone":"0G_TO_PW","pUp":38,"pDown":31,"pPin":31,"magnitude":326,"action":"accelerate","bias":0.07,"intensity":0.4},{"regime":"NEUTRAL","zone":"BELOW_PW","pUp":43,"pDown":36,"pPin":21,"magnitude":415,"action":"capitulate","bias":0.07,"intensity":0.55},{"regime":"SHORT_GAMMA","zone":"ABOVE_CALL","pUp":63,"pDown":16,"pPin":21,"magnitude":564,"action":"accelerate","bias":0.47,"intensity":0.85},{"regime":"SHORT_GAMMA","zone":"CW_TO_0G","pUp":53,"pDown":21,"pPin":26,"magnitude":376,"action":"accelerate","bias":0.32,"intensity":0.65},{"regime":"SHORT_GAMMA","zone":"AT_0G","pUp":43,"pDown":36,"pPin":21,"magnitude":470,"action":"accelerate","bias":0.07,"intensity":0.7},{"regime":"SHORT_GAMMA","zone":"0G_TO_PW","pUp":28,"pDown":46,"pPin":26,"magnitude":517,"action":"accelerate","bias":-0.18,"intensity":0.8},{"regime":"SHORT_GAMMA","zone":"BELOW_PW","pUp":18,"pDown":61,"pPin":21,"magnitude":658,"action":"capitulate","bias":-0.43,"intensity":0.95},{"regime":"VANNA_DRIVEN","zone":"ABOVE_CALL","pUp":33,"pDown":46,"pPin":21,"magnitude":460,"action":"fade","bias":-0.13,"intensity":0.65},{"regime":"VANNA_DRIVEN","zone":"CW_TO_0G","pUp":38,"pDown":36,"pPin":26,"magnitude":307,"action":"fade","bias":0.02,"intensity":0.55},{"regime":"VANNA_DRIVEN","zone":"AT_0G","pUp":38,"pDown":31,"pPin":31,"magnitude":383,"action":"fade","bias":0.07,"intensity":0.4},{"regime":"VANNA_DRIVEN","zone":"0G_TO_PW","pUp":33,"pDown":41,"pPin":26,"magnitude":422,"action":"accelerate","bias":-0.08,"intensity":0.7},{"regime":"VANNA_DRIVEN","zone":"BELOW_PW","pUp":28,"pDown":51,"pPin":21,"magnitude":537,"action":"capitulate","bias":-0.23,"intensity":0.85},{"regime":"CHARM_DRIVEN","zone":"ABOVE_CALL","pUp":31,"pDown":49,"pPin":20,"magnitude":293,"action":"fade","bias":-0.18,"intensity":0.7},{"regime":"CHARM_DRIVEN","zone":"CW_TO_0G","pUp":26,"pDown":34,"pPin":40,"magnitude":195,"action":"pin","bias":-0.08,"intensity":0.65},{"regime":"CHARM_DRIVEN","zone":"AT_0G","pUp":31,"pDown":19,"pPin":50,"magnitude":244,"action":"pin","bias":0.12,"intensity":0.9},{"regime":"CHARM_DRIVEN","zone":"0G_TO_PW","pUp":46,"pDown":14,"pPin":40,"magnitude":268,"action":"pin","bias":0.32,"intensity":0.65},{"regime":"CHARM_DRIVEN","zone":"BELOW_PW","pUp":61,"pDown":19,"pPin":20,"magnitude":341,"action":"defend","bias":0.42,"intensity":0.7}],"notes":{"regime":"OPEX proximity (0D) + charm tightening — delta rebalance pressure into close","zone":"Between 0-Γ (7204) and Call Wall (7270) — mid-range positive gamma","summary":"Dealers likely pin spot — 40% pinned, ~195pt move"}}},"quarterly":{"horizon":"quarterly","label":"SPX QUARTERLY MODEL","symbol":"^GSPC","displaySymbol":"SPX","spot":7244.33,"spotAnchorDate":"FRI 5/1","targetDate":"FRI 8/21","targetDateLong":"FRI AUG 21, 2026","priceRange":[6843.23206934736,7645.42793065264],"rangeBox":{"low":7219.762751747525,"high":7269.899993079105,"width":50.1372413315803,"widthPct":0.6920894179528031,"breakoutTrigger":7269.899993079105,"breakdownTrigger":7219.762751747525,"status":"contained","anchorHigh":{"name":"CALL WALL","kind":"callWall"},"anchorLow":{"name":"STRONG MAG","kind":"strongMag"}},"levels":[{"label":"UPPER VOMMA 8,022","name":"UPPER VOMMA","price":8021.958613052806,"kind":"upperVomma","gex":29877339.378096092,"tag":"TAIL","note":"Upside vomma pocket — IV-churn zone","distBps":1073,"side":"resistance","status":"held"},{"label":"T2 UP 7,645","name":"T2 UP","price":7645.42793065264,"kind":"t2Up","distBps":554,"side":"resistance","status":"held"},{"label":"T1 UP 7,445","name":"T1 UP","price":7444.878965326319,"kind":"t1Up","distBps":277,"side":"resistance","status":"held"},{"label":"UPSIDE PIVOT 7,306","name":"UPSIDE PIVOT","price":7306.2494930445,"kind":"upsidePivot","tag":"VOMMA","distBps":85,"side":"resistance","status":"held"},{"label":"CALL WALL 7,270","name":"CALL WALL","price":7269.899993079105,"kind":"callWall","gex":1364556132.9077115,"tag":"CEILING","distBps":35,"side":"resistance","status":"held"},{"label":"DOMINANT MAG 7,270","name":"DOMINANT MAG","price":7269.899993079105,"kind":"dominantMag","gex":1189825236.58052,"tag":"MAG","distBps":35,"side":"resistance","status":"held"},{"label":"CHARM TGT 7,270","name":"CHARM TARGET","price":7269.899993079105,"kind":"charmTarget","gex":1189825236.58052,"tag":"DECAY","note":"Charm-decay magnet — dealers re-hedge toward here into close","distBps":35,"side":"resistance","status":"held"},{"label":"STRONG MAG 7,220","name":"STRONG MAG","price":7219.762751747525,"kind":"strongMag","gex":909566837.6538959,"tag":"MAG","distBps":-34,"side":"support","status":"held"},{"label":"ZERO-Γ FLIP 7,195","name":"ZERO-Γ FLIP","price":7195.268964998537,"kind":"zeroGamma","tag":"FLIP","distBps":-68,"side":"support","status":"held"},{"label":"ZOMMA BRIDGE 7,183","name":"ZOMMA BRIDGE","price":7182.937372881356,"kind":"zommaBridge","tag":"SHELF","note":"∂Vega/∂σ shelf — vol-expansion support","distBps":-85,"side":"support","status":"held"},{"label":"T1 DOWN 7,044","name":"T1 DOWN","price":7043.781034673681,"kind":"t1Down","distBps":-277,"side":"support","status":"held"},{"label":"PUT WALL 7,019","name":"PUT WALL","price":7019.213786421205,"kind":"putWall","gex":-1288686948.041191,"tag":"FLOOR","distBps":-311,"side":"support","status":"held"},{"label":"EXTREME VAC 7,019","name":"EXTREME VAC","price":7019.213786421205,"kind":"extremeVac","gex":-812726650.2757763,"tag":"VAC","note":"Liquidity vacuum — moves extend here","distBps":-311,"side":"support","status":"held"},{"label":"MOPEX MAX PAIN 7,019","name":"MOPEX MAX PAIN","price":7019.213786421205,"kind":"mopexMaxPain","tag":"PIN","distBps":-311,"side":"support","status":"held"},{"label":"DOWNSIDE PIVOT 6,984","name":"DOWNSIDE PIVOT","price":6984.117717489099,"kind":"downsidePivot","tag":"VOMMA","distBps":-359,"side":"support","status":"held"},{"label":"T2 DOWN 6,843","name":"T2 DOWN","price":6843.23206934736,"kind":"t2Down","distBps":-554,"side":"support","status":"held"},{"label":"LOWER VOMMA 6,518","name":"LOWER VOMMA","price":6517.841373105404,"kind":"lowerVomma","gex":-231562787.3765786,"tag":"TAIL","note":"Downside vomma pocket — IV-churn zone","distBps":-1003,"side":"support","status":"held"}],"paths":[{"kind":"base","name":"BASE","probability":0.45,"target":7269.899993079105,"waypoints":[{"label":"FRI 5/1","t":0,"price":7244.33},{"label":"FRI 6/19","t":0.3333333333333333,"price":7257.556893528285},{"label":"FRI 7/17","t":0.6666666666666666,"price":7264.378221644291},{"label":"FRI 8/21 7,270","t":1,"price":7269.899993079105}],"color":"base"},{"kind":"bull","name":"BULL","probability":0.3,"target":7306.2494930445,"waypoints":[{"label":"FRI 5/1","t":0,"price":7244.33},{"label":"FRI 6/19","t":0.3333333333333333,"price":7264.969831014833},{"label":"FRI 7/17","t":0.6666666666666666,"price":7285.609662029667},{"label":"FRI 8/21 7,306","t":1,"price":7306.2494930445}],"color":"bull"},{"kind":"bear","name":"BEAR","probability":0.25,"target":6984.117717489099,"waypoints":[{"label":"FRI 5/1","t":0,"price":7244.33},{"label":"FRI 6/19","t":0.3333333333333333,"price":7195.268964998537},{"label":"FRI 7/17","t":0.6666666666666666,"price":7089.6933412438175},{"label":"FRI 8/21 6,984","t":1,"price":6984.117717489099}],"color":"bear"}],"audit":{"asOf":1777664743,"spot":7244.33,"spotChange":"","slope":"DN 2.00° → -4.15","path":"grind down into pin","opexGravity":"311pt below 7,019 ↓ 3.1%","gexTotal":3510964820.7130566,"dex":162.27280548641997,"charmPerDay":-4.1542328849846175,"netCTrue":-2098823452.1688569,"vexPerVolPct":2.5188829889433015,"vannaBias":"positive","vannaM":2518.9,"gammaZone":"y+","gammaZoneLabel":"DAMPENING","gammaAtSpot":3511,"dfi":5,"dfiLabel":"BULLISH","dfiFlipped":false,"contractCount":4791,"mainPivot":7195.268964998537,"charmZero":null,"doubleZeroLow":null,"doubleZeroHigh":null,"scenarioProb":{"bull":26,"base":53,"bear":21},"scenarioTargets":{"bull":7286.15,"base":7244.33,"bear":7202.51,"oneDayEM":41.82},"closeTargets":{"bull":{"price":7306.2494930445,"prob":26},"base":{"price":7269.899993079105,"prob":53},"bear":{"price":6984.117717489099,"prob":21}},"lastRecal":{"at":1777664743,"dfi":5,"dfiDeltaSinceOpen":0},"termStructureDoD":{"iv1d":1.0494813533889542,"iv1dPrev":1.0639699915209746,"iv1dDelta":-0.014488638132020393,"charmNow":-4.15,"charmPrev":-2.5439421120786263,"label":"Charm Pressing"},"charmZeros":[],"charmTightening":{"rate":12.47,"label":"DECEL","chopFlag":true,"note":"DECEL above 3 — charm tightening fast, chop risk into close"},"nearby":[{"price":8021.958613052806,"note":"1073bp · UPPER VOMMA","dir":"up"},{"price":7306.2494930445,"note":"85bp · UPSIDE PIVOT","dir":"up"},{"price":7269.899993079105,"note":"35bp · CALL WALL","dir":"up"},{"price":7269.899993079105,"note":"35bp · DOMINANT MAG","dir":"up"},{"price":7269.899993079105,"note":"35bp · CHARM TARGET","dir":"up"},{"price":7219.762751747525,"note":"-34bp · STRONG MAG","dir":"down"}]},"vol":{"vix":16.66,"vixChangePct":-1.3617489518051709,"termRatio":1.2046818727490995,"termLabel":"contango (calm front-end)"},"vomma":"normal","confidence":"MODERATE","mmMatrix":{"asOf":1777664743,"currentRegime":"CHARM_DRIVEN","currentZone":"CW_TO_0G","regimes":["LONG_GAMMA","NEUTRAL","SHORT_GAMMA","VANNA_DRIVEN","CHARM_DRIVEN"],"zones":["ABOVE_CALL","CW_TO_0G","AT_0G","0G_TO_PW","BELOW_PW"],"cells":[{"regime":"LONG_GAMMA","zone":"ABOVE_CALL","pUp":23,"pDown":46,"pPin":31,"magnitude":398,"action":"fade","bias":-0.23,"intensity":0.75},{"regime":"LONG_GAMMA","zone":"CW_TO_0G","pUp":28,"pDown":16,"pPin":56,"magnitude":266,"action":"pin","bias":0.12,"intensity":0.85},{"regime":"LONG_GAMMA","zone":"AT_0G","pUp":38,"pDown":26,"pPin":36,"magnitude":332,"action":"pin","bias":0.12,"intensity":0.45},{"regime":"LONG_GAMMA","zone":"0G_TO_PW","pUp":38,"pDown":16,"pPin":46,"magnitude":365,"action":"defend","bias":0.22,"intensity":0.6},{"regime":"LONG_GAMMA","zone":"BELOW_PW","pUp":58,"pDown":11,"pPin":31,"magnitude":465,"action":"defend","bias":0.47,"intensity":0.75},{"regime":"NEUTRAL","zone":"ABOVE_CALL","pUp":38,"pDown":36,"pPin":26,"magnitude":616,"action":"fade","bias":0.02,"intensity":0.45},{"regime":"NEUTRAL","zone":"CW_TO_0G","pUp":38,"pDown":26,"pPin":36,"magnitude":410,"action":"pin","bias":0.12,"intensity":0.4},{"regime":"NEUTRAL","zone":"AT_0G","pUp":43,"pDown":31,"pPin":26,"magnitude":513,"action":"fade","bias":0.12,"intensity":0.3},{"regime":"NEUTRAL","zone":"0G_TO_PW","pUp":38,"pDown":31,"pPin":31,"magnitude":564,"action":"accelerate","bias":0.07,"intensity":0.4},{"regime":"NEUTRAL","zone":"BELOW_PW","pUp":43,"pDown":36,"pPin":21,"magnitude":718,"action":"capitulate","bias":0.07,"intensity":0.55},{"regime":"SHORT_GAMMA","zone":"ABOVE_CALL","pUp":63,"pDown":16,"pPin":21,"magnitude":978,"action":"accelerate","bias":0.47,"intensity":0.85},{"regime":"SHORT_GAMMA","zone":"CW_TO_0G","pUp":53,"pDown":21,"pPin":26,"magnitude":652,"action":"accelerate","bias":0.32,"intensity":0.65},{"regime":"SHORT_GAMMA","zone":"AT_0G","pUp":43,"pDown":36,"pPin":21,"magnitude":815,"action":"accelerate","bias":0.07,"intensity":0.7},{"regime":"SHORT_GAMMA","zone":"0G_TO_PW","pUp":28,"pDown":46,"pPin":26,"magnitude":896,"action":"accelerate","bias":-0.18,"intensity":0.8},{"regime":"SHORT_GAMMA","zone":"BELOW_PW","pUp":18,"pDown":61,"pPin":21,"magnitude":1141,"action":"capitulate","bias":-0.43,"intensity":0.95},{"regime":"VANNA_DRIVEN","zone":"ABOVE_CALL","pUp":33,"pDown":46,"pPin":21,"magnitude":797,"action":"fade","bias":-0.13,"intensity":0.65},{"regime":"VANNA_DRIVEN","zone":"CW_TO_0G","pUp":38,"pDown":36,"pPin":26,"magnitude":531,"action":"fade","bias":0.02,"intensity":0.55},{"regime":"VANNA_DRIVEN","zone":"AT_0G","pUp":38,"pDown":31,"pPin":31,"magnitude":664,"action":"fade","bias":0.07,"intensity":0.4},{"regime":"VANNA_DRIVEN","zone":"0G_TO_PW","pUp":33,"pDown":41,"pPin":26,"magnitude":730,"action":"accelerate","bias":-0.08,"intensity":0.7},{"regime":"VANNA_DRIVEN","zone":"BELOW_PW","pUp":28,"pDown":51,"pPin":21,"magnitude":929,"action":"capitulate","bias":-0.23,"intensity":0.85},{"regime":"CHARM_DRIVEN","zone":"ABOVE_CALL","pUp":31,"pDown":49,"pPin":20,"magnitude":507,"action":"fade","bias":-0.18,"intensity":0.7},{"regime":"CHARM_DRIVEN","zone":"CW_TO_0G","pUp":25,"pDown":35,"pPin":40,"magnitude":338,"action":"pin","bias":-0.1,"intensity":0.65},{"regime":"CHARM_DRIVEN","zone":"AT_0G","pUp":31,"pDown":19,"pPin":50,"magnitude":422,"action":"pin","bias":0.12,"intensity":0.9},{"regime":"CHARM_DRIVEN","zone":"0G_TO_PW","pUp":46,"pDown":14,"pPin":40,"magnitude":465,"action":"pin","bias":0.32,"intensity":0.65},{"regime":"CHARM_DRIVEN","zone":"BELOW_PW","pUp":61,"pDown":19,"pPin":20,"magnitude":591,"action":"defend","bias":0.42,"intensity":0.7}],"notes":{"regime":"OPEX proximity (0D) + charm tightening — delta rebalance pressure into close","zone":"Between 0-Γ (7195) and Call Wall (7270) — mid-range positive gamma","summary":"Dealers likely pin spot — 40% pinned, ~338pt move"}}}},"warnings":[],"experimental":true}}